build/lib/mcli/__init__.py
build/lib/mcli/__main__.py
build/lib/mcli/config.py
build/lib/mcli/logging.py
build/lib/mcli/main.py
build/lib/mcli/paths.py
build/lib/mcli/template.py
build/lib/mcli/commands/__init__.py
build/lib/mcli/commands/build.py
build/lib/mcli/commands/cache.py
build/lib/mcli/commands/clean.py
build/lib/mcli/commands/config.py
build/lib/mcli/commands/create.py
build/lib/mcli/commands/install.py
build/lib/mcli/commands/publish.py
build/lib/mcli/commands/reload_deps.py
build/lib/mcli/commands/run.py
build/lib/mcli/commands/setup.py
build/lib/mcli/commands/test.py
build/lib/mcli/commands/toolchain.py
build/lib/mcli/package/__init__.py
build/lib/mcli/package/conan.py
build/lib/mcli/package/deps.py
build/lib/mcli/toolchain/__init__.py
build/lib/mcli/toolchain/base.py
build/lib/mcli/toolchain/conan_profile.py
build/lib/mcli/toolchain/manager.py
build/lib/mcli/toolchain/toolchain.py
build/lib/tests/test_cache.py
build/lib/tests/test_template.py
mclang_cli-0.1.7.dist-info/licenses/LICENSE
mcli/__init__.py
mcli/__main__.py
mcli/config.py
mcli/logging.py
mcli/main.py
mcli/paths.py
mcli/template.py
mcli/commands/__init__.py
mcli/commands/build.py
mcli/commands/cache.py
mcli/commands/clean.py
mcli/commands/config.py
mcli/commands/create.py
mcli/commands/install.py
mcli/commands/publish.py
mcli/commands/reload_deps.py
mcli/commands/run.py
mcli/commands/setup.py
mcli/commands/test.py
mcli/commands/toolchain.py
mcli/package/__init__.py
mcli/package/conan.py
mcli/package/deps.py
mcli/templates/conanbase.py.mct
mcli/templates/project/app/mclang.toml.mct
mcli/templates/project/app/meson.build.mct
mcli/templates/project/app/pyrightconfig.json
mcli/templates/project/app/template.toml
mcli/templates/project/app/src/main.py.mct
mcli/templates/project/app/src/meson.build.mct
mcli/templates/project/app/tests/main.py.mct
mcli/templates/project/app/tests/meson.build.mct
mcli/templates/project/app/tests/test_{{ project_name }}.py.mct
mcli/templates/project/module/mclang.toml.mct
mclang_cli-0.1.7.dist-info/METADATA
mclang_cli-0.1.7.dist-info/WHEEL
mclang_cli-0.1.7.dist-info/entry_points.txt
mclang_cli-0.1.7.dist-info/top_level.txt
mclang_cli-0.1.7.dist-info/RECORD
