Metadata-Version: 2.4
Name: mclang-cli
Version: 0.1.7
Summary: MCLang CLI - MCLang 项目管理工具
Home-page: https://gitcode.com/zjp99/mcli
Author: MCLang Development Team
Author-email: MCLang Development Team <mclang@openubmc.com>
Maintainer-email: MCLang Development Team <mclang@openubmc.com>
License: Mulan PSL v2
Project-URL: Homepage, https://gitcode.com/openubmc/mcli
Project-URL: Documentation, https://gitcode.com/openubmc/mcli
Project-URL: Repository, https://gitcode.com/openubmc/mcli
Project-URL: Issues, https://gitcode.com/openubmc/mcli/issues
Keywords: compiler,code-generator,python,cpp,transpiler,build-tools,project-management
Classifier: Development Status :: 3 - Alpha
Classifier: Intended Audience :: Developers
Classifier: Topic :: Software Development :: Code Generators
Classifier: Topic :: Software Development :: Compilers
Classifier: Topic :: Software Development :: Build Tools
Classifier: License :: OSI Approved
Classifier: Programming Language :: Python :: 3
Classifier: Programming Language :: Python :: 3.11
Classifier: Programming Language :: Python :: 3.12
Classifier: Programming Language :: Python :: 3.13
Classifier: Programming Language :: C++
Requires-Python: >=3.11
License-File: LICENSE
Requires-Dist: meson>=1.0
Requires-Dist: ninja>=1.10
Requires-Dist: conan>=2.0.0
Requires-Dist: mclang-compiler<0.4.0,>=0.3.0
Provides-Extra: dev
Requires-Dist: pytest>=7.0.0; extra == "dev"
Requires-Dist: psutil>=5.8.0; extra == "dev"
Dynamic: author
Dynamic: home-page
Dynamic: license-file
Dynamic: requires-python
